Shift Register/shiftRegister.v
/*
Authored by Elijah Theander
October 20,2016
shiftRegister.v
This shift register will hold 96 bits,
4 instances of 24 bits for GRB diodes.
Upon recieving notice of one bit's generation completing 
it will rotate left, eventually going through all bits.
*/

module shiftRegister(registerBit,loadRegister,loadValue,genDone,clk,reset);

	output registerBit;			//output bit going to controller
	input loadRegister;			//control input guiding loading
	input [95:0] loadValue;		//value to be loaded in upon loadRegister going high
	input genDone;				//using this to dictate rotation
	input clk,reset;			//synchronous clock and reset.

	reg [95:0] S,nS;			//state memory variable, also the register.
	
	parameter DEFAULT = 96'h0F0F0F_0F0F0F_0F0F0F_0F0F0F;
	
	//State Memory
	always @(posedge clk)begin
		if(reset)begin
			S <= DEFAULT;
		end
		else begin
			S <= nS;
		end
	end
	
	//Next state block
	always @(S,loadRegister,loadValue,genDone)begin
		case({loadRegister,genDone})
			2'b00:	nS = S;
			2'b01:	nS = {S[94:0],S[95]};//rotate left everytime a bit is generated.
			2'b10:	nS = loadValue;
			2'b11:	nS = loadValue;      //giving loadRegister precedence.
		endcase
	end
	
	assign registerBit = S[95];
	
endmodule

Test Benches/tb_shiftRegister.v
/*
Authored by Elijah Theander
October 27, 2016
tb_shiftRegister.v
Test bench verifying the function
of shiftRegister.v 
*/

`timescale 1ns/1ns

module tb_shiftRegister;

	wire 		 registerBit;
	reg  		 loadRegister;
	reg [95:0]   loadValue;
	reg 		 genDone;
	reg 		 clk,reset;
	
	//module under test
	shiftRegister mut(registerBit,loadRegister,loadValue,genDone,clk,reset);
	
	//100Mhz clk
	always begin
		#5 clk = !clk;
	end
	
	initial begin
		$dumpfile("shiftreg.vcd");
		$dumpvars(0,tb_shiftRegister);
			loadValue = 96'hAAAAAA_BBBBBB_AAAAAA_BBBBBB;
			{loadRegister,genDone,clk,reset} =4'b1101;		#20
			reset = 0;										#20
			loadregister = 0;								#1000 //this should give us all rotates.
		$finish;
	end
	
endmodule

Test bench results/shiftRegister/shiftreg.vcd
$date
	Thu Oct 27 12:53:23 2016
$end
$version
	Icarus Verilog
$end
$timescale
	1ns
$end
$scope module tb_shiftRegister $end
$var wire 1 ! registerBit $end
$var reg 1 " clk $end
$var reg 1 # genDone $end
$var reg 1 $ loadRegister $end
$var reg 96 % loadValue [95:0] $end
$var reg 1 & reset $end
$scope module mut $end
$var wire 1 " clk $end
$var wire 1 # genDone $end
$var wire 1 $ loadRegister $end
$var wire 96 ' loadValue [95:0] $end
$var wire 1 & reset $end
$var wire 1 ! registerBit $end
$var reg 96 ( S [95:0] $end
$var reg 96 ) nS [95:0] $end
$upscope $end
$upscope $end
$enddefinitions $end
#0
$dumpvars
b101010101010101010101010101110111011101110111011101010101010101010101010101110111011101110111011 )
bx (
b101010101010101010101010101110111011101110111011101010101010101010101010101110111011101110111011 '
1&
b101010101010101010101010101110111011101110111011101010101010101010101010101110111011101110111011 %
1$
1#
0"
x!
$end
#5
0!
b11110000111100001111000011110000111100001111000011110000111100001111000011110000111100001111 (
1"
#10
0"
#15
1"
#20
0"
0&
#25
1!
b101010101010101010101010101110111011101110111011101010101010101010101010101110111011101110111011 (
1"
#30
0"
#35
1"
#40
b10101010101010101010101011101110111011101110111010101010101010101010101011101110111011101110111 )
0"
0$
#45
b101010101010101010101010111011101110111011101110101010101010101010101010111011101110111011101110 )
0!
b10101010101010101010101011101110111011101110111010101010101010101010101011101110111011101110111 (
1"
#50
0"
#55
b10101010101010101010101110111011101110111011101010101010101010101010101110111011101110111011101 )
1!
b101010101010101010101010111011101110111011101110101010101010101010101010111011101110111011101110 (
1"
#60
0"
#65
b101010101010101010101011101110111011101110111010101010101010101010101011101110111011101110111010 )
0!
b10101010101010101010101110111011101110111011101010101010101010101010101110111011101110111011101 (
1"
#70
0"
#75
b10101010101010101010111011101110111011101110101010101010101010101010111011101110111011101110101 )
1!
b101010101010101010101011101110111011101110111010101010101010101010101011101110111011101110111010 (
1"
#80
0"
#85
b101010101010101010101110111011101110111011101010101010101010101010101110111011101110111011101010 )
0!
b10101010101010101010111011101110111011101110101010101010101010101010111011101110111011101110101 (
1"
#90
0"
#95
b10101010101010101011101110111011101110111010101010101010101010101011101110111011101110111010101 )
1!
b101010101010101010101110111011101110111011101010101010101010101010101110111011101110111011101010 (
1"
#100
0"
#105
b101010101010101010111011101110111011101110101010101010101010101010111011101110111011101110101010 )
0!
b10101010101010101011101110111011101110111010101010101010101010101011101110111011101110111010101 (
1"
#110
0"
#115
b10101010101010101110111011101110111011101010101010101010101010101110111011101110111011101010101 )
1!
b101010101010101010111011101110111011101110101010101010101010101010111011101110111011101110101010 (
1"
#120
0"
#125
b101010101010101011101110111011101110111010101010101010101010101011101110111011101110111010101010 )
0!
b10101010101010101110111011101110111011101010101010101010101010101110111011101110111011101010101 (
1"
#130
0"
#135
b10101010101010111011101110111011101110101010101010101010101010111011101110111011101110101010101 )
1!
b101010101010101011101110111011101110111010101010101010101010101011101110111011101110111010101010 (
1"
#140
0"
#145
b101010101010101110111011101110111011101010101010101010101010101110111011101110111011101010101010 )
0!
b10101010101010111011101110111011101110101010101010101010101010111011101110111011101110101010101 (
1"
#150
0"
#155
b10101010101011101110111011101110111010101010101010101010101011101110111011101110111010101010101 )
1!
b101010101010101110111011101110111011101010101010101010101010101110111011101110111011101010101010 (
1"
#160
0"
#165
b101010101010111011101110111011101110101010101010101010101010111011101110111011101110101010101010 )
0!
b10101010101011101110111011101110111010101010101010101010101011101110111011101110111010101010101 (
1"
#170
0"
#175
b10101010101110111011101110111011101010101010101010101010101110111011101110111011101010101010101 )
1!
b101010101010111011101110111011101110101010101010101010101010111011101110111011101110101010101010 (
1"
#180
0"
#185
b101010101011101110111011101110111010101010101010101010101011101110111011101110111010101010101010 )
0!
b10101010101110111011101110111011101010101010101010101010101110111011101110111011101010101010101 (
1"
#190
0"
#195
b10101010111011101110111011101110101010101010101010101010111011101110111011101110101010101010101 )
1!
b101010101011101110111011101110111010101010101010101010101011101110111011101110111010101010101010 (
1"
#200
0"
#205
b101010101110111011101110111011101010101010101010101010101110111011101110111011101010101010101010 )
0!
b10101010111011101110111011101110101010101010101010101010111011101110111011101110101010101010101 (
1"
#210
0"
#215
b10101011101110111011101110111010101010101010101010101011101110111011101110111010101010101010101 )
1!
b101010101110111011101110111011101010101010101010101010101110111011101110111011101010101010101010 (
1"
#220
0"
#225
b101010111011101110111011101110101010101010101010101010111011101110111011101110101010101010101010 )
0!
b10101011101110111011101110111010101010101010101010101011101110111011101110111010101010101010101 (
1"
#230
0"
#235
b10101110111011101110111011101010101010101010101010101110111011101110111011101010101010101010101 )
1!
b101010111011101110111011101110101010101010101010101010111011101110111011101110101010101010101010 (
1"
#240
0"
#245
b101011101110111011101110111010101010101010101010101011101110111011101110111010101010101010101010 )
0!
b10101110111011101110111011101010101010101010101010101110111011101110111011101010101010101010101 (
1"
#250
0"
#255
b10111011101110111011101110101010101010101010101010111011101110111011101110101010101010101010101 )
1!
b101011101110111011101110111010101010101010101010101011101110111011101110111010101010101010101010 (
1"
#260
0"
#265
b101110111011101110111011101010101010101010101010101110111011101110111011101010101010101010101010 )
0!
b10111011101110111011101110101010101010101010101010111011101110111011101110101010101010101010101 (
1"
#270
0"
#275
b11101110111011101110111010101010101010101010101011101110111011101110111010101010101010101010101 )
1!
b101110111011101110111011101010101010101010101010101110111011101110111011101010101010101010101010 (
1"
#280
0"
#285
b111011101110111011101110101010101010101010101010111011101110111011101110101010101010101010101010 )
0!
b11101110111011101110111010101010101010101010101011101110111011101110111010101010101010101010101 (
1"
#290
0"
#295
b110111011101110111011101010101010101010101010101110111011101110111011101010101010101010101010101 )
1!
b111011101110111011101110101010101010101010101010111011101110111011101110101010101010101010101010 (
1"
#300
0"
#305
b101110111011101110111010101010101010101010101011101110111011101110111010101010101010101010101011 )
b110111011101110111011101010101010101010101010101110111011101110111011101010101010101010101010101 (
1"
#310
0"
#315
b11101110111011101110101010101010101010101010111011101110111011101110101010101010101010101010111 )
b101110111011101110111010101010101010101010101011101110111011101110111010101010101010101010101011 (
1"
#320
0"
#325
b111011101110111011101010101010101010101010101110111011101110111011101010101010101010101010101110 )
0!
b11101110111011101110101010101010101010101010111011101110111011101110101010101010101010101010111 (
1"
#330
0"
#335
b110111011101110111010101010101010101010101011101110111011101110111010101010101010101010101011101 )
1!
b111011101110111011101010101010101010101010101110111011101110111011101010101010101010101010101110 (
1"
#340
0"
#345
b101110111011101110101010101010101010101010111011101110111011101110101010101010101010101010111011 )
b110111011101110111010101010101010101010101011101110111011101110111010101010101010101010101011101 (
1"
#350
0"
#355
b11101110111011101010101010101010101010101110111011101110111011101010101010101010101010101110111 )
b101110111011101110101010101010101010101010111011101110111011101110101010101010101010101010111011 (
1"
#360
0"
#365
b111011101110111010101010101010101010101011101110111011101110111010101010101010101010101011101110 )
0!
b11101110111011101010101010101010101010101110111011101110111011101010101010101010101010101110111 (
1"
#370
0"
#375
b110111011101110101010101010101010101010111011101110111011101110101010101010101010101010111011101 )
1!
b111011101110111010101010101010101010101011101110111011101110111010101010101010101010101011101110 (
1"
#380
0"
#385
b101110111011101010101010101010101010101110111011101110111011101010101010101010101010101110111011 )
b110111011101110101010101010101010101010111011101110111011101110101010101010101010101010111011101 (
1"
#390
0"
#395
b11101110111010101010101010101010101011101110111011101110111010101010101010101010101011101110111 )
b101110111011101010101010101010101010101110111011101110111011101010101010101010101010101110111011 (
1"
#400
0"
#405
b111011101110101010101010101010101010111011101110111011101110101010101010101010101010111011101110 )
0!
b11101110111010101010101010101010101011101110111011101110111010101010101010101010101011101110111 (
1"
#410
0"
#415
b110111011101010101010101010101010101110111011101110111011101010101010101010101010101110111011101 )
1!
b111011101110101010101010101010101010111011101110111011101110101010101010101010101010111011101110 (
1"
#420
0"
#425
b101110111010101010101010101010101011101110111011101110111010101010101010101010101011101110111011 )
b110111011101010101010101010101010101110111011101110111011101010101010101010101010101110111011101 (
1"
#430
0"
#435
b11101110101010101010101010101010111011101110111011101110101010101010101010101010111011101110111 )
b101110111010101010101010101010101011101110111011101110111010101010101010101010101011101110111011 (
1"
#440
0"
#445
b111011101010101010101010101010101110111011101110111011101010101010101010101010101110111011101110 )
0!
b11101110101010101010101010101010111011101110111011101110101010101010101010101010111011101110111 (
1"
#450
0"
#455
b110111010101010101010101010101011101110111011101110111010101010101010101010101011101110111011101 )
1!
b111011101010101010101010101010101110111011101110111011101010101010101010101010101110111011101110 (
1"
#460
0"
#465
b101110101010101010101010101010111011101110111011101110101010101010101010101010111011101110111011 )
b110111010101010101010101010101011101110111011101110111010101010101010101010101011101110111011101 (
1"
#470
0"
#475
b11101010101010101010101010101110111011101110111011101010101010101010101010101110111011101110111 )
b101110101010101010101010101010111011101110111011101110101010101010101010101010111011101110111011 (
1"
#480
0"
#485
b111010101010101010101010101011101110111011101110111010101010101010101010101011101110111011101110 )
0!
b11101010101010101010101010101110111011101110111011101010101010101010101010101110111011101110111 (
1"
#490
0"
#495
b110101010101010101010101010111011101110111011101110101010101010101010101010111011101110111011101 )
1!
b111010101010101010101010101011101110111011101110111010101010101010101010101011101110111011101110 (
1"
#500
0"
#505
b101010101010101010101010101110111011101110111011101010101010101010101010101110111011101110111011 )
b110101010101010101010101010111011101110111011101110101010101010101010101010111011101110111011101 (
1"
#510
0"
#515
b10101010101010101010101011101110111011101110111010101010101010101010101011101110111011101110111 )
b101010101010101010101010101110111011101110111011101010101010101010101010101110111011101110111011 (
1"
#520
0"
#525
b101010101010101010101010111011101110111011101110101010101010101010101010111011101110111011101110 )
0!
b10101010101010101010101011101110111011101110111010101010101010101010101011101110111011101110111 (
1"
#530
0"
#535
b10101010101010101010101110111011101110111011101010101010101010101010101110111011101110111011101 )
1!
b101010101010101010101010111011101110111011101110101010101010101010101010111011101110111011101110 (
1"
#540
0"
#545
b101010101010101010101011101110111011101110111010101010101010101010101011101110111011101110111010 )
0!
b10101010101010101010101110111011101110111011101010101010101010101010101110111011101110111011101 (
1"
#550
0"
#555
b10101010101010101010111011101110111011101110101010101010101010101010111011101110111011101110101 )
1!
b101010101010101010101011101110111011101110111010101010101010101010101011101110111011101110111010 (
1"
#560
0"
#565
b101010101010101010101110111011101110111011101010101010101010101010101110111011101110111011101010 )
0!
b10101010101010101010111011101110111011101110101010101010101010101010111011101110111011101110101 (
1"
#570
0"
#575
b10101010101010101011101110111011101110111010101010101010101010101011101110111011101110111010101 )
1!
b101010101010101010101110111011101110111011101010101010101010101010101110111011101110111011101010 (
1"
#580
0"
#585
b101010101010101010111011101110111011101110101010101010101010101010111011101110111011101110101010 )
0!
b10101010101010101011101110111011101110111010101010101010101010101011101110111011101110111010101 (
1"
#590
0"
#595
b10101010101010101110111011101110111011101010101010101010101010101110111011101110111011101010101 )
1!
b101010101010101010111011101110111011101110101010101010101010101010111011101110111011101110101010 (
1"
#600
0"
#605
b101010101010101011101110111011101110111010101010101010101010101011101110111011101110111010101010 )
0!
b10101010101010101110111011101110111011101010101010101010101010101110111011101110111011101010101 (
1"
#610
0"
#615
b10101010101010111011101110111011101110101010101010101010101010111011101110111011101110101010101 )
1!
b101010101010101011101110111011101110111010101010101010101010101011101110111011101110111010101010 (
1"
#620
0"
#625
b101010101010101110111011101110111011101010101010101010101010101110111011101110111011101010101010 )
0!
b10101010101010111011101110111011101110101010101010101010101010111011101110111011101110101010101 (
1"
#630
0"
#635
b10101010101011101110111011101110111010101010101010101010101011101110111011101110111010101010101 )
1!
b101010101010101110111011101110111011101010101010101010101010101110111011101110111011101010101010 (
1"
#640
0"
#645
b101010101010111011101110111011101110101010101010101010101010111011101110111011101110101010101010 )
0!
b10101010101011101110111011101110111010101010101010101010101011101110111011101110111010101010101 (
1"
#650
0"
#655
b10101010101110111011101110111011101010101010101010101010101110111011101110111011101010101010101 )
1!
b101010101010111011101110111011101110101010101010101010101010111011101110111011101110101010101010 (
1"
#660
0"
#665
b101010101011101110111011101110111010101010101010101010101011101110111011101110111010101010101010 )
0!
b10101010101110111011101110111011101010101010101010101010101110111011101110111011101010101010101 (
1"
#670
0"
#675
b10101010111011101110111011101110101010101010101010101010111011101110111011101110101010101010101 )
1!
b101010101011101110111011101110111010101010101010101010101011101110111011101110111010101010101010 (
1"
#680
0"
#685
b101010101110111011101110111011101010101010101010101010101110111011101110111011101010101010101010 )
0!
b10101010111011101110111011101110101010101010101010101010111011101110111011101110101010101010101 (
1"
#690
0"
#695
b10101011101110111011101110111010101010101010101010101011101110111011101110111010101010101010101 )
1!
b101010101110111011101110111011101010101010101010101010101110111011101110111011101010101010101010 (
1"
#700
0"
#705
b101010111011101110111011101110101010101010101010101010111011101110111011101110101010101010101010 )
0!
b10101011101110111011101110111010101010101010101010101011101110111011101110111010101010101010101 (
1"
#710
0"
#715
b10101110111011101110111011101010101010101010101010101110111011101110111011101010101010101010101 )
1!
b101010111011101110111011101110101010101010101010101010111011101110111011101110101010101010101010 (
1"
#720
0"
#725
b101011101110111011101110111010101010101010101010101011101110111011101110111010101010101010101010 )
0!
b10101110111011101110111011101010101010101010101010101110111011101110111011101010101010101010101 (
1"
#730
0"
#735
b10111011101110111011101110101010101010101010101010111011101110111011101110101010101010101010101 )
1!
b101011101110111011101110111010101010101010101010101011101110111011101110111010101010101010101010 (
1"
#740
0"
#745
b101110111011101110111011101010101010101010101010101110111011101110111011101010101010101010101010 )
0!
b10111011101110111011101110101010101010101010101010111011101110111011101110101010101010101010101 (
1"
#750
0"
#755
b11101110111011101110111010101010101010101010101011101110111011101110111010101010101010101010101 )
1!
b101110111011101110111011101010101010101010101010101110111011101110111011101010101010101010101010 (
1"
#760
0"
#765
b111011101110111011101110101010101010101010101010111011101110111011101110101010101010101010101010 )
0!
b11101110111011101110111010101010101010101010101011101110111011101110111010101010101010101010101 (
1"
#770
0"
#775
b110111011101110111011101010101010101010101010101110111011101110111011101010101010101010101010101 )
1!
b111011101110111011101110101010101010101010101010111011101110111011101110101010101010101010101010 (
1"
#780
0"
#785
b101110111011101110111010101010101010101010101011101110111011101110111010101010101010101010101011 )
b110111011101110111011101010101010101010101010101110111011101110111011101010101010101010101010101 (
1"
#790
0"
#795
b11101110111011101110101010101010101010101010111011101110111011101110101010101010101010101010111 )
b101110111011101110111010101010101010101010101011101110111011101110111010101010101010101010101011 (
1"
#800
0"
#805
b111011101110111011101010101010101010101010101110111011101110111011101010101010101010101010101110 )
0!
b11101110111011101110101010101010101010101010111011101110111011101110101010101010101010101010111 (
1"
#810
0"
#815
b110111011101110111010101010101010101010101011101110111011101110111010101010101010101010101011101 )
1!
b111011101110111011101010101010101010101010101110111011101110111011101010101010101010101010101110 (
1"
#820
0"
#825
b101110111011101110101010101010101010101010111011101110111011101110101010101010101010101010111011 )
b110111011101110111010101010101010101010101011101110111011101110111010101010101010101010101011101 (
1"
#830
0"
#835
b11101110111011101010101010101010101010101110111011101110111011101010101010101010101010101110111 )
b101110111011101110101010101010101010101010111011101110111011101110101010101010101010101010111011 (
1"
#840
0"
#845
b111011101110111010101010101010101010101011101110111011101110111010101010101010101010101011101110 )
0!
b11101110111011101010101010101010101010101110111011101110111011101010101010101010101010101110111 (
1"
#850
0"
#855
b110111011101110101010101010101010101010111011101110111011101110101010101010101010101010111011101 )
1!
b111011101110111010101010101010101010101011101110111011101110111010101010101010101010101011101110 (
1"
#860
0"
#865
b101110111011101010101010101010101010101110111011101110111011101010101010101010101010101110111011 )
b110111011101110101010101010101010101010111011101110111011101110101010101010101010101010111011101 (
1"
#870
0"
#875
b11101110111010101010101010101010101011101110111011101110111010101010101010101010101011101110111 )
b101110111011101010101010101010101010101110111011101110111011101010101010101010101010101110111011 (
1"
#880
0"
#885
b111011101110101010101010101010101010111011101110111011101110101010101010101010101010111011101110 )
0!
b11101110111010101010101010101010101011101110111011101110111010101010101010101010101011101110111 (
1"
#890
0"
#895
b110111011101010101010101010101010101110111011101110111011101010101010101010101010101110111011101 )
1!
b111011101110101010101010101010101010111011101110111011101110101010101010101010101010111011101110 (
1"
#900
0"
#905
b101110111010101010101010101010101011101110111011101110111010101010101010101010101011101110111011 )
b110111011101010101010101010101010101110111011101110111011101010101010101010101010101110111011101 (
1"
#910
0"
#915
b11101110101010101010101010101010111011101110111011101110101010101010101010101010111011101110111 )
b101110111010101010101010101010101011101110111011101110111010101010101010101010101011101110111011 (
1"
#920
0"
#925
b111011101010101010101010101010101110111011101110111011101010101010101010101010101110111011101110 )
0!
b11101110101010101010101010101010111011101110111011101110101010101010101010101010111011101110111 (
1"
#930
0"
#935
b110111010101010101010101010101011101110111011101110111010101010101010101010101011101110111011101 )
1!
b111011101010101010101010101010101110111011101110111011101010101010101010101010101110111011101110 (
1"
#940
0"
#945
b101110101010101010101010101010111011101110111011101110101010101010101010101010111011101110111011 )
b110111010101010101010101010101011101110111011101110111010101010101010101010101011101110111011101 (
1"
#950
0"
#955
b11101010101010101010101010101110111011101110111011101010101010101010101010101110111011101110111 )
b101110101010101010101010101010111011101110111011101110101010101010101010101010111011101110111011 (
1"
#960
0"
#965
b111010101010101010101010101011101110111011101110111010101010101010101010101011101110111011101110 )
0!
b11101010101010101010101010101110111011101110111011101010101010101010101010101110111011101110111 (
1"
#970
0"
#975
b110101010101010101010101010111011101110111011101110101010101010101010101010111011101110111011101 )
1!
b111010101010101010101010101011101110111011101110111010101010101010101010101011101110111011101110 (
1"
#980
0"
#985
b101010101010101010101010101110111011101110111011101010101010101010101010101110111011101110111011 )
b110101010101010101010101010111011101110111011101110101010101010101010101010111011101110111011101 (
1"
#990
0"
#995
b10101010101010101010101011101110111011101110111010101010101010101010101011101110111011101110111 )
b101010101010101010101010101110111011101110111011101010101010101010101010101110111011101110111011 (
1"
#1000
0"
#1005
b101010101010101010101010111011101110111011101110101010101010101010101010111011101110111011101110 )
0!
b10101010101010101010101011101110111011101110111010101010101010101010101011101110111011101110111 (
1"
#1010
0"
#1015
b10101010101010101010101110111011101110111011101010101010101010101010101110111011101110111011101 )
1!
b101010101010101010101010111011101110111011101110101010101010101010101010111011101110111011101110 (
1"
#1020
0"
#1025
b101010101010101010101011101110111011101110111010101010101010101010101011101110111011101110111010 )
0!
b10101010101010101010101110111011101110111011101010101010101010101010101110111011101110111011101 (
1"
#1030
0"
#1035
b10101010101010101010111011101110111011101110101010101010101010101010111011101110111011101110101 )
1!
b101010101010101010101011101110111011101110111010101010101010101010101011101110111011101110111010 (
1"
