Shift Register/weeWoo.v
/*
Authored by Elijah Theander
October 28, 2016
weeWoo.v
This module takes a tenHzDiv input and uses it to swap 
the leading color of a register.
*/

module weeWoo(rbSwap,tenHzIn,clk,reset);
	output [95:0] rbSwap;     //output of register
	
	input         tenHzIn;    //input from tenHzDiv saying when to swap reg
	input         clk,reset;
	
	//State Variables;
	reg           S;
	wire          nS;
	
	//Register parameters
	parameter redfirst  = 96'h00F000_0000F0_00F000_0000F0;
	parameter bluefirst = 96'h0000F0_00F000_0000F0_00F000;
	
	//State Memory
	always @(posedge clk)begin
		if(reset)begin
			S <= 1'b0;
		end
		else begin
			S <= nS;
		end
	end
	
	//Next state based on tenHzIn.
	assign nS = (tenHzIn)? !S:S;
	
	//rbSwap out
	assign rbSwap = S? redfirst:bluefirst;
	
endmodule

Test Benches/tb_weeWoo.v
/*
Authored by Elijah Theander
November 2, 2016
tb_weeWoo.v
Test bench linking tenhzdiv and weewoo.v
to verify weewoo.v
*/

`timescale 1ns/1ns

module tb_weeWoo;

	wire [95:0] rbSwap;
	
	reg         tenHzIn;
	reg         clk,reset;
	
	//Module under test
	weeWoo   mut(rbSwap,tenHzIn,clk,reset);
	
	//100 MHz clk
	always begin
	    #5 clk = !clk;
	end
	
	//Begin testing stimulus
	initial begin
	    $dumpfile("weeWoo.vcd");
		$dumpvars(0,tb_weeWoo);
		    {tenHzIn,clk,reset} = 3'b101; #30
			reset = 0;                    #30
			tenHzIn = 0;                  #30
			tenHzIn = 1;                  #30
			tenHzIn = 0;                  #30
			//This should give us several changes.
		$finish;
	end
	
endmodule

Test bench results/weeWoo/weeWoo.vcd
$date
	Fri Nov 04 13:54:20 2016
$end
$version
	Icarus Verilog
$end
$timescale
	1ns
$end
$scope module tb_weeWoo $end
$var wire 96 ! rbSwap [95:0] $end
$var reg 1 " clk $end
$var reg 1 # reset $end
$var reg 1 $ tenHzIn $end
$scope module mut $end
$var wire 1 % clk $end
$var wire 1 & nS $end
$var wire 96 ' rbSwap [95:0] $end
$var wire 1 ( reset $end
$var wire 1 ) tenHzIn $end
$var reg 1 * S $end
$upscope $end
$upscope $end
$enddefinitions $end
#0
$dumpvars
x*
1)
1(
b0xxxx0000xxxx000000000000xxxx0000xxxx000000000000xxxx0000xxxx000000000000xxxx0000xxxx0000 '
x&
0%
1$
1#
0"
b0xxxx0000xxxx000000000000xxxx0000xxxx000000000000xxxx0000xxxx000000000000xxxx0000xxxx0000 !
$end
#5
1&
b11110000000000001111000000000000000000000000000011110000000000001111000000000000 !
b11110000000000001111000000000000000000000000000011110000000000001111000000000000 '
0*
1"
1%
#10
0"
0%
#15
1"
1%
#20
0"
0%
#25
1"
1%
#30
0"
0%
0#
0(
#35
0&
b1111000000000000000000000000000011110000000000001111000000000000000000000000000011110000 !
b1111000000000000000000000000000011110000000000001111000000000000000000000000000011110000 '
1*
1"
1%
#40
0"
0%
#45
1&
b11110000000000001111000000000000000000000000000011110000000000001111000000000000 !
b11110000000000001111000000000000000000000000000011110000000000001111000000000000 '
0*
1"
1%
#50
0"
0%
#55
0&
b1111000000000000000000000000000011110000000000001111000000000000000000000000000011110000 !
b1111000000000000000000000000000011110000000000001111000000000000000000000000000011110000 '
1*
1"
1%
#60
1&
0"
0%
0$
0)
#65
1"
1%
#70
0"
0%
#75
1"
1%
#80
0"
0%
#85
1"
1%
#90
0&
0"
0%
1$
1)
#95
1&
b11110000000000001111000000000000000000000000000011110000000000001111000000000000 !
b11110000000000001111000000000000000000000000000011110000000000001111000000000000 '
0*
1"
1%
#100
0"
0%
#105
0&
b1111000000000000000000000000000011110000000000001111000000000000000000000000000011110000 !
b1111000000000000000000000000000011110000000000001111000000000000000000000000000011110000 '
1*
1"
1%
#110
0"
0%
#115
1&
b11110000000000001111000000000000000000000000000011110000000000001111000000000000 !
b11110000000000001111000000000000000000000000000011110000000000001111000000000000 '
0*
1"
1%
#120
0&
0"
0%
0$
0)
