Shift Register/rainbowReg.v
/*
Authored by Elijah Theander
November 4, 2016
rainbowReg.v
This module takes the clock, reset, and tenHzIn signal and simply
adds one to the value of the register every time tenHzIn goes High.
this reg is split into green red and blue and distributed into a large register.
I am choosing this because If I just let it count through the whole 96 bits it would 
get very, very bright, and I don't exactly feel like searing my retinas off just yet.
*/

module rainbowReg(colorCycle,tenHzIn,clk,reset);
	
	output [95:0] colorCycle;
	
	input         tenHzIn;
	input         clk,reset;
	
	reg    [47:0] S;
	
	always @(posedge clk)begin
		if(reset)begin
			S <= 48'd0;
		end
		else if(tenHzIn)begin
			S <= S+1;
		end
		else begin
			S <= S;
		end
	end
	
	assign colorCycle = {S[47:44],4'h0, S[43:40],4'h0, S[39:36],4'h0,
	                     S[35:32],4'h0, S[31:28],4'h0, S[27:24],4'h0,
						 S[23:20],4'h0, S[19:16],4'h0, S[15:12],4'h0,
						 S[11:8], 4'h0, S[7:4],  4'h0, S[3:0],  4'h0};
						 
endmodule

Test Benches/tb_rainbowReg.v
/*
Authored by Elijah Theander
November 4, 2016
tb_rainbowReg.v
Module for verifying function of rainbowReg.v
*/

`timescale 1ns/1ns

module tb_rainbowReg;

	wire [95:0] colorCycle;
	
	reg tenHzIn;
	reg clk,reset;
	
	//Module under test
	rainbowReg mut(colorCycle,tenHzIn,clk,reset);
	
	//100 MHz clk
	always begin
		#5 clk = !clk;
	end
	
	//Generate pulse for tenHzIn, not actually ten Hz in this bench.
	always begin
		#40 tenHzIn = !tenHzIn;
	end
	
	//Begin testing stimulus
	initial begin
		$dumpfile("rainbowReg.vcd");
		$dumpvars(0,tb_rainbowReg);
		{clk,reset,tenHzIn} = 3'b010; #30
		reset = 0;                    #10_000
		//This should show us a substantial amount of counts
		$finish;
	end
	
endmodule

Test bench results/rainbowReg/rainbowReg.vcd
$date
	Fri Nov 04 16:13:58 2016
$end
$version
	Icarus Verilog
$end
$timescale
	1ns
$end
$scope module tb_rainbowReg $end
$var wire 96 ! colorCycle [95:0] $end
$var reg 1 " clk $end
$var reg 1 # reset $end
$var reg 1 $ tenHzIn $end
$scope module mut $end
$var wire 1 % clk $end
$var wire 96 & colorCycle [95:0] $end
$var wire 1 ' reset $end
$var wire 1 ( tenHzIn $end
$var reg 48 ) S [47:0] $end
$upscope $end
$upscope $end
$enddefinitions $end
#0
$dumpvars
bx )
0(
1'
bx0000xxxx0000xxxx0000xxxx0000xxxx0000xxxx0000xxxx0000xxxx0000xxxx0000xxxx0000xxxx0000xxxx0000 &
0%
0$
1#
0"
bx0000xxxx0000xxxx0000xxxx0000xxxx0000xxxx0000xxxx0000xxxx0000xxxx0000xxxx0000xxxx0000xxxx0000 !
$end
#5
b0 !
b0 &
b0 )
1"
1%
#10
0"
0%
#15
1"
1%
#20
0"
0%
#25
1"
1%
#30
0"
0%
0#
0'
#35
1"
1%
#40
0"
0%
1$
1(
#45
b10000 !
b10000 &
b1 )
1"
1%
#50
0"
0%
#55
b100000 !
b100000 &
b10 )
1"
1%
#60
0"
0%
#65
b110000 !
b110000 &
b11 )
1"
1%
#70
0"
0%
#75
b1000000 !
b1000000 &
b100 )
1"
1%
#80
0"
0%
0$
0(
#85
1"
1%
#90
0"
0%
#95
1"
1%
#100
0"
0%
#105
1"
1%
#110
0"
0%
#115
1"
1%
#120
0"
0%
1$
1(
#125
b1010000 !
b1010000 &
b101 )
1"
1%
#130
0"
0%
#135
b1100000 !
b1100000 &
b110 )
1"
1%
#140
0"
0%
#145
b1110000 !
b1110000 &
b111 )
1"
1%
#150
0"
0%
#155
b10000000 !
b10000000 &
b1000 )
1"
1%
#160
0"
0%
0$
0(
#165
1"
1%
#170
0"
0%
#175
1"
1%
#180
0"
0%
#185
1"
1%
#190
0"
0%
#195
1"
1%
#200
0"
0%
1$
1(
#205
b10010000 !
b10010000 &
b1001 )
1"
1%
#210
0"
0%
#215
b10100000 !
b10100000 &
b1010 )
1"
1%
#220
0"
0%
#225
b10110000 !
b10110000 &
b1011 )
1"
1%
#230
0"
0%
#235
b11000000 !
b11000000 &
b1100 )
1"
1%
#240
0"
0%
0$
0(
#245
1"
1%
#250
0"
0%
#255
1"
1%
#260
0"
0%
#265
1"
1%
#270
0"
0%
#275
1"
1%
#280
0"
0%
1$
1(
#285
b11010000 !
b11010000 &
b1101 )
1"
1%
#290
0"
0%
#295
b11100000 !
b11100000 &
b1110 )
1"
1%
#300
0"
0%
#305
b11110000 !
b11110000 &
b1111 )
1"
1%
#310
0"
0%
#315
b1000000000000 !
b1000000000000 &
b10000 )
1"
1%
#320
0"
0%
0$
0(
#325
1"
1%
#330
0"
0%
#335
1"
1%
#340
0"
0%
#345
1"
1%
#350
0"
0%
#355
1"
1%
#360
0"
0%
1$
1(
#365
b1000000010000 !
b1000000010000 &
b10001 )
1"
1%
#370
0"
0%
#375
b1000000100000 !
b1000000100000 &
b10010 )
1"
1%
#380
0"
0%
#385
b1000000110000 !
b1000000110000 &
b10011 )
1"
1%
#390
0"
0%
#395
b1000001000000 !
b1000001000000 &
b10100 )
1"
1%
#400
0"
0%
0$
0(
#405
1"
1%
#410
0"
0%
#415
1"
1%
#420
0"
0%
#425
1"
1%
#430
0"
0%
#435
1"
1%
#440
0"
0%
1$
1(
#445
b1000001010000 !
b1000001010000 &
b10101 )
1"
1%
#450
0"
0%
#455
b1000001100000 !
b1000001100000 &
b10110 )
1"
1%
#460
0"
0%
#465
b1000001110000 !
b1000001110000 &
b10111 )
1"
1%
#470
0"
0%
#475
b1000010000000 !
b1000010000000 &
b11000 )
1"
1%
#480
0"
0%
0$
0(
#485
1"
1%
#490
0"
0%
#495
1"
1%
#500
0"
0%
#505
1"
1%
#510
0"
0%
#515
1"
1%
#520
0"
0%
1$
1(
#525
b1000010010000 !
b1000010010000 &
b11001 )
1"
1%
#530
0"
0%
#535
b1000010100000 !
b1000010100000 &
b11010 )
1"
1%
#540
0"
0%
#545
b1000010110000 !
b1000010110000 &
b11011 )
1"
1%
#550
0"
0%
#555
b1000011000000 !
b1000011000000 &
b11100 )
1"
1%
#560
0"
0%
0$
0(
#565
1"
1%
#570
0"
0%
#575
1"
1%
#580
0"
0%
#585
1"
1%
#590
0"
0%
#595
1"
1%
#600
0"
0%
1$
1(
#605
b1000011010000 !
b1000011010000 &
b11101 )
1"
1%
#610
0"
0%
#615
b1000011100000 !
b1000011100000 &
b11110 )
1"
1%
#620
0"
0%
#625
b1000011110000 !
b1000011110000 &
b11111 )
1"
1%
#630
0"
0%
#635
b10000000000000 !
b10000000000000 &
b100000 )
1"
1%
#640
0"
0%
0$
0(
#645
1"
1%
#650
0"
0%
#655
1"
1%
#660
0"
0%
#665
1"
1%
#670
0"
0%
#675
1"
1%
#680
0"
0%
1$
1(
#685
b10000000010000 !
b10000000010000 &
b100001 )
1"
1%
#690
0"
0%
#695
b10000000100000 !
b10000000100000 &
b100010 )
1"
1%
#700
0"
0%
#705
b10000000110000 !
b10000000110000 &
b100011 )
1"
1%
#710
0"
0%
#715
b10000001000000 !
b10000001000000 &
b100100 )
1"
1%
#720
0"
0%
0$
0(
#725
1"
1%
#730
0"
0%
#735
1"
1%
#740
0"
0%
#745
1"
1%
#750
0"
0%
#755
1"
1%
#760
0"
0%
1$
1(
#765
b10000001010000 !
b10000001010000 &
b100101 )
1"
1%
#770
0"
0%
#775
b10000001100000 !
b10000001100000 &
b100110 )
1"
1%
#780
0"
0%
#785
b10000001110000 !
b10000001110000 &
b100111 )
1"
1%
#790
0"
0%
#795
b10000010000000 !
b10000010000000 &
b101000 )
1"
1%
#800
0"
0%
0$
0(
#805
1"
1%
#810
0"
0%
#815
1"
1%
#820
0"
0%
#825
1"
1%
#830
0"
0%
#835
1"
1%
#840
0"
0%
1$
1(
#845
b10000010010000 !
b10000010010000 &
b101001 )
1"
1%
#850
0"
0%
#855
b10000010100000 !
b10000010100000 &
b101010 )
1"
1%
#860
0"
0%
#865
b10000010110000 !
b10000010110000 &
b101011 )
1"
1%
#870
0"
0%
#875
b10000011000000 !
b10000011000000 &
b101100 )
1"
1%
#880
0"
0%
0$
0(
#885
1"
1%
#890
0"
0%
#895
1"
1%
#900
0"
0%
#905
1"
1%
#910
0"
0%
#915
1"
1%
#920
0"
0%
1$
1(
#925
b10000011010000 !
b10000011010000 &
b101101 )
1"
1%
#930
0"
0%
#935
b10000011100000 !
b10000011100000 &
b101110 )
1"
1%
#940
0"
0%
#945
b10000011110000 !
b10000011110000 &
b101111 )
1"
1%
#950
0"
0%
#955
b11000000000000 !
b11000000000000 &
b110000 )
1"
1%
#960
0"
0%
0$
0(
#965
1"
1%
#970
0"
0%
#975
1"
1%
#980
0"
0%
#985
1"
1%
#990
0"
0%
#995
1"
1%
#1000
0"
0%
1$
1(
#1005
b11000000010000 !
b11000000010000 &
b110001 )
1"
1%
#1010
0"
0%
#1015
b11000000100000 !
b11000000100000 &
b110010 )
1"
1%
#1020
0"
0%
#1025
b11000000110000 !
b11000000110000 &
b110011 )
1"
1%
#1030
0"
0%
#1035
b11000001000000 !
b11000001000000 &
b110100 )
1"
1%
#1040
0"
0%
0$
0(
#1045
1"
1%
#1050
0"
0%
#1055
1"
1%
#1060
0"
0%
#1065
1"
1%
#1070
0"
0%
#1075
1"
1%
#1080
0"
0%
1$
1(
#1085
b11000001010000 !
b11000001010000 &
b110101 )
1"
1%
#1090
0"
0%
#1095
b11000001100000 !
b11000001100000 &
b110110 )
1"
1%
#1100
0"
0%
#1105
b11000001110000 !
b11000001110000 &
b110111 )
1"
1%
#1110
0"
0%
#1115
b11000010000000 !
b11000010000000 &
b111000 )
1"
1%
#1120
0"
0%
0$
0(
#1125
1"
1%
#1130
0"
0%
#1135
1"
1%
#1140
0"
0%
#1145
1"
1%
#1150
0"
0%
#1155
1"
1%
#1160
0"
0%
1$
1(
#1165
b11000010010000 !
b11000010010000 &
b111001 )
1"
1%
#1170
0"
0%
#1175
b11000010100000 !
b11000010100000 &
b111010 )
1"
1%
#1180
0"
0%
#1185
b11000010110000 !
b11000010110000 &
b111011 )
1"
1%
#1190
0"
0%
#1195
b11000011000000 !
b11000011000000 &
b111100 )
1"
1%
#1200
0"
0%
0$
0(
#1205
1"
1%
#1210
0"
0%
#1215
1"
1%
#1220
0"
0%
#1225
1"
1%
#1230
0"
0%
#1235
1"
1%
#1240
0"
0%
1$
1(
#1245
b11000011010000 !
b11000011010000 &
b111101 )
1"
1%
#1250
0"
0%
#1255
b11000011100000 !
b11000011100000 &
b111110 )
1"
1%
#1260
0"
0%
#1265
b11000011110000 !
b11000011110000 &
b111111 )
1"
1%
#1270
0"
0%
#1275
b100000000000000 !
b100000000000000 &
b1000000 )
1"
1%
#1280
0"
0%
0$
0(
#1285
1"
1%
#1290
0"
0%
#1295
1"
1%
#1300
0"
0%
#1305
1"
1%
#1310
0"
0%
#1315
1"
1%
#1320
0"
0%
1$
1(
#1325
b100000000010000 !
b100000000010000 &
b1000001 )
1"
1%
#1330
0"
0%
#1335
b100000000100000 !
b100000000100000 &
b1000010 )
1"
1%
#1340
0"
0%
#1345
b100000000110000 !
b100000000110000 &
b1000011 )
1"
1%
#1350
0"
0%
#1355
b100000001000000 !
b100000001000000 &
b1000100 )
1"
1%
#1360
0"
0%
0$
0(
#1365
1"
1%
#1370
0"
0%
#1375
1"
1%
#1380
0"
0%
#1385
1"
1%
#1390
0"
0%
#1395
1"
1%
#1400
0"
0%
1$
1(
#1405
b100000001010000 !
b100000001010000 &
b1000101 )
1"
1%
#1410
0"
0%
#1415
b100000001100000 !
b100000001100000 &
b1000110 )
1"
1%
#1420
0"
0%
#1425
b100000001110000 !
b100000001110000 &
b1000111 )
1"
1%
#1430
0"
0%
#1435
b100000010000000 !
b100000010000000 &
b1001000 )
1"
1%
#1440
0"
0%
0$
0(
#1445
1"
1%
#1450
0"
0%
#1455
1"
1%
#1460
0"
0%
#1465
1"
1%
#1470
0"
0%
#1475
1"
1%
#1480
0"
0%
1$
1(
#1485
b100000010010000 !
b100000010010000 &
b1001001 )
1"
1%
#1490
0"
0%
#1495
b100000010100000 !
b100000010100000 &
b1001010 )
1"
1%
#1500
0"
0%
#1505
b100000010110000 !
b100000010110000 &
b1001011 )
1"
1%
#1510
0"
0%
#1515
b100000011000000 !
b100000011000000 &
b1001100 )
1"
1%
#1520
0"
0%
0$
0(
#1525
1"
1%
#1530
0"
0%
#1535
1"
1%
#1540
0"
0%
#1545
1"
1%
#1550
0"
0%
#1555
1"
1%
#1560
0"
0%
1$
1(
#1565
b100000011010000 !
b100000011010000 &
b1001101 )
1"
1%
#1570
0"
0%
#1575
b100000011100000 !
b100000011100000 &
b1001110 )
1"
1%
#1580
0"
0%
#1585
b100000011110000 !
b100000011110000 &
b1001111 )
1"
1%
#1590
0"
0%
#1595
b101000000000000 !
b101000000000000 &
b1010000 )
1"
1%
#1600
0"
0%
0$
0(
#1605
1"
1%
#1610
0"
0%
#1615
1"
1%
#1620
0"
0%
#1625
1"
1%
#1630
0"
0%
#1635
1"
1%
#1640
0"
0%
1$
1(
#1645
b101000000010000 !
b101000000010000 &
b1010001 )
1"
1%
#1650
0"
0%
#1655
b101000000100000 !
b101000000100000 &
b1010010 )
1"
1%
#1660
0"
0%
#1665
b101000000110000 !
b101000000110000 &
b1010011 )
1"
1%
#1670
0"
0%
#1675
b101000001000000 !
b101000001000000 &
b1010100 )
1"
1%
#1680
0"
0%
0$
0(
#1685
1"
1%
#1690
0"
0%
#1695
1"
1%
#1700
0"
0%
#1705
1"
1%
#1710
0"
0%
#1715
1"
1%
#1720
0"
0%
1$
1(
#1725
b101000001010000 !
b101000001010000 &
b1010101 )
1"
1%
#1730
0"
0%
#1735
b101000001100000 !
b101000001100000 &
b1010110 )
1"
1%
#1740
0"
0%
#1745
b101000001110000 !
b101000001110000 &
b1010111 )
1"
1%
#1750
0"
0%
#1755
b101000010000000 !
b101000010000000 &
b1011000 )
1"
1%
#1760
0"
0%
0$
0(
#1765
1"
1%
#1770
0"
0%
#1775
1"
1%
#1780
0"
0%
#1785
1"
1%
#1790
0"
0%
#1795
1"
1%
#1800
0"
0%
1$
1(
#1805
b101000010010000 !
b101000010010000 &
b1011001 )
1"
1%
#1810
0"
0%
#1815
b101000010100000 !
b101000010100000 &
b1011010 )
1"
1%
#1820
0"
0%
#1825
b101000010110000 !
b101000010110000 &
b1011011 )
1"
1%
#1830
0"
0%
#1835
b101000011000000 !
b101000011000000 &
b1011100 )
1"
1%
#1840
0"
0%
0$
0(
#1845
1"
1%
#1850
0"
0%
#1855
1"
1%
#1860
0"
0%
#1865
1"
1%
#1870
0"
0%
#1875
1"
1%
#1880
0"
0%
1$
1(
#1885
b101000011010000 !
b101000011010000 &
b1011101 )
1"
1%
#1890
0"
0%
#1895
b101000011100000 !
b101000011100000 &
b1011110 )
1"
1%
#1900
0"
0%
#1905
b101000011110000 !
b101000011110000 &
b1011111 )
1"
1%
#1910
0"
0%
#1915
b110000000000000 !
b110000000000000 &
b1100000 )
1"
1%
#1920
0"
0%
0$
0(
#1925
1"
1%
#1930
0"
0%
#1935
1"
1%
#1940
0"
0%
#1945
1"
1%
#1950
0"
0%
#1955
1"
1%
#1960
0"
0%
1$
1(
#1965
b110000000010000 !
b110000000010000 &
b1100001 )
1"
1%
#1970
0"
0%
#1975
b110000000100000 !
b110000000100000 &
b1100010 )
1"
1%
#1980
0"
0%
#1985
b110000000110000 !
b110000000110000 &
b1100011 )
1"
1%
#1990
0"
0%
#1995
b110000001000000 !
b110000001000000 &
b1100100 )
1"
1%
#2000
0"
0%
0$
0(
#2005
1"
1%
#2010
0"
0%
#2015
1"
1%
#2020
0"
0%
#2025
1"
1%
#2030
0"
0%
#2035
1"
1%
#2040
0"
0%
1$
1(
#2045
b110000001010000 !
b110000001010000 &
b1100101 )
1"
1%
#2050
0"
0%
#2055
b110000001100000 !
b110000001100000 &
b1100110 )
1"
1%
#2060
0"
0%
#2065
b110000001110000 !
b110000001110000 &
b1100111 )
1"
1%
#2070
0"
0%
#2075
b110000010000000 !
b110000010000000 &
b1101000 )
1"
1%
#2080
0"
0%
0$
0(
#2085
1"
1%
#2090
0"
0%
#2095
1"
1%
#2100
0"
0%
#2105
1"
1%
#2110
0"
0%
#2115
1"
1%
#2120
0"
0%
1$
1(
#2125
b110000010010000 !
b110000010010000 &
b1101001 )
1"
1%
#2130
0"
0%
#2135
b110000010100000 !
b110000010100000 &
b1101010 )
1"
1%
#2140
0"
0%
#2145
b110000010110000 !
b110000010110000 &
b1101011 )
1"
1%
#2150
0"
0%
#2155
b110000011000000 !
b110000011000000 &
b1101100 )
1"
1%
#2160
0"
0%
0$
0(
#2165
1"
1%
#2170
0"
0%
#2175
1"
1%
#2180
0"
0%
#2185
1"
1%
#2190
0"
0%
#2195
1"
1%
#2200
0"
0%
1$
1(
#2205
b110000011010000 !
b110000011010000 &
b1101101 )
1"
1%
#2210
0"
0%
#2215
b110000011100000 !
b110000011100000 &
b1101110 )
1"
1%
#2220
0"
0%
#2225
b110000011110000 !
b110000011110000 &
b1101111 )
1"
1%
#2230
0"
0%
#2235
b111000000000000 !
b111000000000000 &
b1110000 )
1"
1%
#2240
0"
0%
0$
0(
#2245
1"
1%
#2250
0"
0%
#2255
1"
1%
#2260
0"
0%
#2265
1"
1%
#2270
0"
0%
#2275
1"
1%
#2280
0"
0%
1$
1(
#2285
b111000000010000 !
b111000000010000 &
b1110001 )
1"
1%
#2290
0"
0%
#2295
b111000000100000 !
b111000000100000 &
b1110010 )
1"
1%
#2300
0"
0%
#2305
b111000000110000 !
b111000000110000 &
b1110011 )
1"
1%
#2310
0"
0%
#2315
b111000001000000 !
b111000001000000 &
b1110100 )
1"
1%
#2320
0"
0%
0$
0(
#2325
1"
1%
#2330
0"
0%
#2335
1"
1%
#2340
0"
0%
#2345
1"
1%
#2350
0"
0%
#2355
1"
1%
#2360
0"
0%
1$
1(
#2365
b111000001010000 !
b111000001010000 &
b1110101 )
1"
1%
#2370
0"
0%
#2375
b111000001100000 !
b111000001100000 &
b1110110 )
1"
1%
#2380
0"
0%
#2385
b111000001110000 !
b111000001110000 &
b1110111 )
1"
1%
#2390
0"
0%
#2395
b111000010000000 !
b111000010000000 &
b1111000 )
1"
1%
#2400
0"
0%
0$
0(
#2405
1"
1%
#2410
0"
0%
#2415
1"
1%
#2420
0"
0%
#2425
1"
1%
#2430
0"
0%
#2435
1"
1%
#2440
0"
0%
1$
1(
#2445
b111000010010000 !
b111000010010000 &
b1111001 )
1"
1%
#2450
0"
0%
#2455
b111000010100000 !
b111000010100000 &
b1111010 )
1"
1%
#2460
0"
0%
#2465
b111000010110000 !
b111000010110000 &
b1111011 )
1"
1%
#2470
0"
0%
#2475
b111000011000000 !
b111000011000000 &
b1111100 )
1"
1%
#2480
0"
0%
0$
0(
#2485
1"
1%
#2490
0"
0%
#2495
1"
1%
#2500
0"
0%
#2505
1"
1%
#2510
0"
0%
#2515
1"
1%
#2520
0"
0%
1$
1(
#2525
b111000011010000 !
b111000011010000 &
b1111101 )
1"
1%
#2530
0"
0%
#2535
b111000011100000 !
b111000011100000 &
b1111110 )
1"
1%
#2540
0"
0%
#2545
b111000011110000 !
b111000011110000 &
b1111111 )
1"
1%
#2550
0"
0%
#2555
b1000000000000000 !
b1000000000000000 &
b10000000 )
1"
1%
#2560
0"
0%
0$
0(
#2565
1"
1%
#2570
0"
0%
#2575
1"
1%
#2580
0"
0%
#2585
1"
1%
#2590
0"
0%
#2595
1"
1%
#2600
0"
0%
1$
1(
#2605
b1000000000010000 !
b1000000000010000 &
b10000001 )
1"
1%
#2610
0"
0%
#2615
b1000000000100000 !
b1000000000100000 &
b10000010 )
1"
1%
#2620
0"
0%
#2625
b1000000000110000 !
b1000000000110000 &
b10000011 )
1"
1%
#2630
0"
0%
#2635
b1000000001000000 !
b1000000001000000 &
b10000100 )
1"
1%
#2640
0"
0%
0$
0(
#2645
1"
1%
#2650
0"
0%
#2655
1"
1%
#2660
0"
0%
#2665
1"
1%
#2670
0"
0%
#2675
1"
1%
#2680
0"
0%
1$
1(
#2685
b1000000001010000 !
b1000000001010000 &
b10000101 )
1"
1%
#2690
0"
0%
#2695
b1000000001100000 !
b1000000001100000 &
b10000110 )
1"
1%
#2700
0"
0%
#2705
b1000000001110000 !
b1000000001110000 &
b10000111 )
1"
1%
#2710
0"
0%
#2715
b1000000010000000 !
b1000000010000000 &
b10001000 )
1"
1%
#2720
0"
0%
0$
0(
#2725
1"
1%
#2730
0"
0%
#2735
1"
1%
#2740
0"
0%
#2745
1"
1%
#2750
0"
0%
#2755
1"
1%
#2760
0"
0%
1$
1(
#2765
b1000000010010000 !
b1000000010010000 &
b10001001 )
1"
1%
#2770
0"
0%
#2775
b1000000010100000 !
b1000000010100000 &
b10001010 )
1"
1%
#2780
0"
0%
#2785
b1000000010110000 !
b1000000010110000 &
b10001011 )
1"
1%
#2790
0"
0%
#2795
b1000000011000000 !
b1000000011000000 &
b10001100 )
1"
1%
#2800
0"
0%
0$
0(
#2805
1"
1%
#2810
0"
0%
#2815
1"
1%
#2820
0"
0%
#2825
1"
1%
#2830
0"
0%
#2835
1"
1%
#2840
0"
0%
1$
1(
#2845
b1000000011010000 !
b1000000011010000 &
b10001101 )
1"
1%
#2850
0"
0%
#2855
b1000000011100000 !
b1000000011100000 &
b10001110 )
1"
1%
#2860
0"
0%
#2865
b1000000011110000 !
b1000000011110000 &
b10001111 )
1"
1%
#2870
0"
0%
#2875
b1001000000000000 !
b1001000000000000 &
b10010000 )
1"
1%
#2880
0"
0%
0$
0(
#2885
1"
1%
#2890
0"
0%
#2895
1"
1%
#2900
0"
0%
#2905
1"
1%
#2910
0"
0%
#2915
1"
1%
#2920
0"
0%
1$
1(
#2925
b1001000000010000 !
b1001000000010000 &
b10010001 )
1"
1%
#2930
0"
0%
#2935
b1001000000100000 !
b1001000000100000 &
b10010010 )
1"
1%
#2940
0"
0%
#2945
b1001000000110000 !
b1001000000110000 &
b10010011 )
1"
1%
#2950
0"
0%
#2955
b1001000001000000 !
b1001000001000000 &
b10010100 )
1"
1%
#2960
0"
0%
0$
0(
#2965
1"
1%
#2970
0"
0%
#2975
1"
1%
#2980
0"
0%
#2985
1"
1%
#2990
0"
0%
#2995
1"
1%
#3000
0"
0%
1$
1(
#3005
b1001000001010000 !
b1001000001010000 &
b10010101 )
1"
1%
#3010
0"
0%
#3015
b1001000001100000 !
b1001000001100000 &
b10010110 )
1"
1%
#3020
0"
0%
#3025
b1001000001110000 !
b1001000001110000 &
b10010111 )
1"
1%
#3030
0"
0%
#3035
b1001000010000000 !
b1001000010000000 &
b10011000 )
1"
1%
#3040
0"
0%
0$
0(
#3045
1"
1%
#3050
0"
0%
#3055
1"
1%
#3060
0"
0%
#3065
1"
1%
#3070
0"
0%
#3075
1"
1%
#3080
0"
0%
1$
1(
#3085
b1001000010010000 !
b1001000010010000 &
b10011001 )
1"
1%
#3090
0"
0%
#3095
b1001000010100000 !
b1001000010100000 &
b10011010 )
1"
1%
#3100
0"
0%
#3105
b1001000010110000 !
b1001000010110000 &
b10011011 )
1"
1%
#3110
0"
0%
#3115
b1001000011000000 !
b1001000011000000 &
b10011100 )
1"
1%
#3120
0"
0%
0$
0(
#3125
1"
1%
#3130
0"
0%
#3135
1"
1%
#3140
0"
0%
#3145
1"
1%
#3150
0"
0%
#3155
1"
1%
#3160
0"
0%
1$
1(
#3165
b1001000011010000 !
b1001000011010000 &
b10011101 )
1"
1%
#3170
0"
0%
#3175
b1001000011100000 !
b1001000011100000 &
b10011110 )
1"
1%
#3180
0"
0%
#3185
b1001000011110000 !
b1001000011110000 &
b10011111 )
1"
1%
#3190
0"
0%
#3195
b1010000000000000 !
b1010000000000000 &
b10100000 )
1"
1%
#3200
0"
0%
0$
0(
#3205
1"
1%
#3210
0"
0%
#3215
1"
1%
#3220
0"
0%
#3225
1"
1%
#3230
0"
0%
#3235
1"
1%
#3240
0"
0%
1$
1(
#3245
b1010000000010000 !
b1010000000010000 &
b10100001 )
1"
1%
#3250
0"
0%
#3255
b1010000000100000 !
b1010000000100000 &
b10100010 )
1"
1%
#3260
0"
0%
#3265
b1010000000110000 !
b1010000000110000 &
b10100011 )
1"
1%
#3270
0"
0%
#3275
b1010000001000000 !
b1010000001000000 &
b10100100 )
1"
1%
#3280
0"
0%
0$
0(
#3285
1"
1%
#3290
0"
0%
#3295
1"
1%
#3300
0"
0%
#3305
1"
1%
#3310
0"
0%
#3315
1"
1%
#3320
0"
0%
1$
1(
#3325
b1010000001010000 !
b1010000001010000 &
b10100101 )
1"
1%
#3330
0"
0%
#3335
b1010000001100000 !
b1010000001100000 &
b10100110 )
1"
1%
#3340
0"
0%
#3345
b1010000001110000 !
b1010000001110000 &
b10100111 )
1"
1%
#3350
0"
0%
#3355
b1010000010000000 !
b1010000010000000 &
b10101000 )
1"
1%
#3360
0"
0%
0$
0(
#3365
1"
1%
#3370
0"
0%
#3375
1"
1%
#3380
0"
0%
#3385
1"
1%
#3390
0"
0%
#3395
1"
1%
#3400
0"
0%
1$
1(
#3405
b1010000010010000 !
b1010000010010000 &
b10101001 )
1"
1%
#3410
0"
0%
#3415
b1010000010100000 !
b1010000010100000 &
b10101010 )
1"
1%
#3420
0"
0%
#3425
b1010000010110000 !
b1010000010110000 &
b10101011 )
1"
1%
#3430
0"
0%
#3435
b1010000011000000 !
b1010000011000000 &
b10101100 )
1"
1%
#3440
0"
0%
0$
0(
#3445
1"
1%
#3450
0"
0%
#3455
1"
1%
#3460
0"
0%
#3465
1"
1%
#3470
0"
0%
#3475
1"
1%
#3480
0"
0%
1$
1(
#3485
b1010000011010000 !
b1010000011010000 &
b10101101 )
1"
1%
#3490
0"
0%
#3495
b1010000011100000 !
b1010000011100000 &
b10101110 )
1"
1%
#3500
0"
0%
#3505
b1010000011110000 !
b1010000011110000 &
b10101111 )
1"
1%
#3510
0"
0%
#3515
b1011000000000000 !
b1011000000000000 &
b10110000 )
1"
1%
#3520
0"
0%
0$
0(
#3525
1"
1%
#3530
0"
0%
#3535
1"
1%
#3540
0"
0%
#3545
1"
1%
#3550
0"
0%
#3555
1"
1%
#3560
0"
0%
1$
1(
#3565
b1011000000010000 !
b1011000000010000 &
b10110001 )
1"
1%
#3570
0"
0%
#3575
b1011000000100000 !
b1011000000100000 &
b10110010 )
1"
1%
#3580
0"
0%
#3585
b1011000000110000 !
b1011000000110000 &
b10110011 )
1"
1%
#3590
0"
0%
#3595
b1011000001000000 !
b1011000001000000 &
b10110100 )
1"
1%
#3600
0"
0%
0$
0(
#3605
1"
1%
#3610
0"
0%
#3615
1"
1%
#3620
0"
0%
#3625
1"
1%
#3630
0"
0%
#3635
1"
1%
#3640
0"
0%
1$
1(
#3645
b1011000001010000 !
b1011000001010000 &
b10110101 )
1"
1%
#3650
0"
0%
#3655
b1011000001100000 !
b1011000001100000 &
b10110110 )
1"
1%
#3660
0"
0%
#3665
b1011000001110000 !
b1011000001110000 &
b10110111 )
1"
1%
#3670
0"
0%
#3675
b1011000010000000 !
b1011000010000000 &
b10111000 )
1"
1%
#3680
0"
0%
0$
0(
#3685
1"
1%
#3690
0"
0%
#3695
1"
1%
#3700
0"
0%
#3705
1"
1%
#3710
0"
0%
#3715
1"
1%
#3720
0"
0%
1$
1(
#3725
b1011000010010000 !
b1011000010010000 &
b10111001 )
1"
1%
#3730
0"
0%
#3735
b1011000010100000 !
b1011000010100000 &
b10111010 )
1"
1%
#3740
0"
0%
#3745
b1011000010110000 !
b1011000010110000 &
b10111011 )
1"
1%
#3750
0"
0%
#3755
b1011000011000000 !
b1011000011000000 &
b10111100 )
1"
1%
#3760
0"
0%
0$
0(
#3765
1"
1%
#3770
0"
0%
#3775
1"
1%
#3780
0"
0%
#3785
1"
1%
#3790
0"
0%
#3795
1"
1%
#3800
0"
0%
1$
1(
#3805
b1011000011010000 !
b1011000011010000 &
b10111101 )
1"
1%
#3810
0"
0%
#3815
b1011000011100000 !
b1011000011100000 &
b10111110 )
1"
1%
#3820
0"
0%
#3825
b1011000011110000 !
b1011000011110000 &
b10111111 )
1"
1%
#3830
0"
0%
#3835
b1100000000000000 !
b1100000000000000 &
b11000000 )
1"
1%
#3840
0"
0%
0$
0(
#3845
1"
1%
#3850
0"
0%
#3855
1"
1%
#3860
0"
0%
#3865
1"
1%
#3870
0"
0%
#3875
1"
1%
#3880
0"
0%
1$
1(
#3885
b1100000000010000 !
b1100000000010000 &
b11000001 )
1"
1%
#3890
0"
0%
#3895
b1100000000100000 !
b1100000000100000 &
b11000010 )
1"
1%
#3900
0"
0%
#3905
b1100000000110000 !
b1100000000110000 &
b11000011 )
1"
1%
#3910
0"
0%
#3915
b1100000001000000 !
b1100000001000000 &
b11000100 )
1"
1%
#3920
0"
0%
0$
0(
#3925
1"
1%
#3930
0"
0%
#3935
1"
1%
#3940
0"
0%
#3945
1"
1%
#3950
0"
0%
#3955
1"
1%
#3960
0"
0%
1$
1(
#3965
b1100000001010000 !
b1100000001010000 &
b11000101 )
1"
1%
#3970
0"
0%
#3975
b1100000001100000 !
b1100000001100000 &
b11000110 )
1"
1%
#3980
0"
0%
#3985
b1100000001110000 !
b1100000001110000 &
b11000111 )
1"
1%
#3990
0"
0%
#3995
b1100000010000000 !
b1100000010000000 &
b11001000 )
1"
1%
#4000
0"
0%
0$
0(
#4005
1"
1%
#4010
0"
0%
#4015
1"
1%
#4020
0"
0%
#4025
1"
1%
#4030
0"
0%
#4035
1"
1%
#4040
0"
0%
1$
1(
#4045
b1100000010010000 !
b1100000010010000 &
b11001001 )
1"
1%
#4050
0"
0%
#4055
b1100000010100000 !
b1100000010100000 &
b11001010 )
1"
1%
#4060
0"
0%
