Shift Register/modeMachine.v
/*
Authored by Elijah Theander
October 28, 2016
modeMachine.v
This state machine takes multiple inputs and uses
them to decide what to pass to the shiftRegister as
a load value, and whether or not it will use a button to determine 
sending after RET.
*/

module modeMachine(go,regVal,changeMode,modeSet,send,Green,Red,Blue,rbSwap,colorCycle,clk,reset);

	output          go;                  //Determines sending.
	output [95:0]   regVal;              //Passthrough into ShiftRegister loadValue
	
	input           changeMode;          // Basys 3 button switch
	input [1:0]     modeSet;             //Basys 3 sw[1:0]
	input           send;                //Basys 3 button switch
	input [3:0]     Green,Red,Blue;      //basys 3 sw [15:4]
	input [95:0]    rbSwap,colorCycle;   //inputs from seperate modules
	input           clk,reset;           //synchronous clock and reset.
	
	//State and next state variables
	reg  [1:0]       S;
	wire [1:0]       nS;
	reg [95:0]       regVal;
	
	//State Parameters
	parameter basemode = 2'b00, weewoo = 2'b01, cyclecolor = 2'b10;
	
	//State Memory
	always @(posedge clk)begin
		if(reset)begin
			S <= basemode;
		end
		else if(changeMode)begin
			S <= nS;
		end
		else begin
			S <= S;
		end
	end
	
	//Next state
	assign nS = modeSet;
	
	//go moore output
	assign go = (S == basemode)? send:1'b1;
	
	//regVal output
	always @(S,Green,Red,Blue,rbSwap,colorCycle)begin
		case(S)
			basemode:begin regVal = {Green,4'h0,Red,4'h0,Blue,4'h0,
			                         Green,4'h0,Red,4'h0,Blue,4'h0,
									 Green,4'h0,Red,4'h0,Blue,4'h0,
									 Green,4'h0,Red,4'h0,Blue,4'h0}; end
			weewoo:        regVal = rbSwap;
			cyclecolor:    regVal = colorCycle;
			default:       regVal = 96'h0F0F0F_0F0F0F_0F0F0F_0F0F0F;
		endcase
	end
	
endmodule

Test Benches/tb_modeMachine.v
/*
Authored by Elijah Theander
November 4, 2016
tb_modeMachine.v
Test bench that verifies function of 
modeMachine.v
*/

`timescale 1ns/1ns

module tb_modeMachine;

	wire          go;
	wire [95:0]   regVal;
	
	reg           changeMode;
	reg [1:0]     modeSet;
	reg           send;
	reg [3:0]     Green,Red,Blue;
	reg [95:0]    rbSwap,colorCycle;
	reg           clk,reset;
	
	//Module under test
	modeMachine mut(go,regVal,changeMode,modeSet,send,Green,Red,Blue,rbSwap,colorCycle,clk,reset);
	
	//100 MHz clk
	
	always begin
	    #5 clk = !clk;
	end
	
	//Begin testing stimulus.
	initial begin
		$dumpfile("modeMachine.vcd");
		$dumpvars(0,tb_modeMachine);
			Green = 4'hA; Red = 4'hB; Blue = 4'hC; modeSet = 2'b00; 
			{changeMode,send,clk,reset} = 4'b0001;  
			rbSwap = 96'hBEE_DAD_BEE_DAD_BEE_DAD_BEE_DAD;
			colorCycle = 96'hCAB_FAD_CAB_FAD_CAB_FAD_CAB_FAD;            #30
			reset = 0;  send = 1;                                        #30
			//I'm going to skip a line and switch indentation for readability here.
			//should be in basemode here. regVal will red green and blue loaded into it.
			
			modeSet = 2'b01; send = 0;          #30 //Mode won't change here
			changeMode = 1;                     #30 //Mode should be 01 after this.
			changeMode = 0;                     #30 //Go should be high, regVal should be BEEDAD
			modeSet = 2'b10; changeMode = 1;    #30 //Mode will be 10, go is High, regVal is CABFAD.
		$finish;
	end
	
endmodule

Test bench results/modeMachine/modeMachine.vcd
$date
	Fri Nov 04 14:44:54 2016
$end
$version
	Icarus Verilog
$end
$timescale
	1ns
$end
$scope module tb_modeMachine $end
$var wire 1 ! go $end
$var wire 96 " regVal [95:0] $end
$var reg 4 # Blue [3:0] $end
$var reg 4 $ Green [3:0] $end
$var reg 4 % Red [3:0] $end
$var reg 1 & changeMode $end
$var reg 1 ' clk $end
$var reg 96 ( colorCycle [95:0] $end
$var reg 2 ) modeSet [1:0] $end
$var reg 96 * rbSwap [95:0] $end
$var reg 1 + reset $end
$var reg 1 , send $end
$scope module mut $end
$var wire 4 - Blue [3:0] $end
$var wire 4 . Green [3:0] $end
$var wire 4 / Red [3:0] $end
$var wire 1 0 changeMode $end
$var wire 1 1 clk $end
$var wire 96 2 colorCycle [95:0] $end
$var wire 1 ! go $end
$var wire 2 3 modeSet [1:0] $end
$var wire 2 4 nS [1:0] $end
$var wire 96 5 rbSwap [95:0] $end
$var wire 1 6 reset $end
$var wire 1 7 send $end
$var reg 2 8 S [1:0] $end
$var reg 96 9 regVal [95:0] $end
$upscope $end
$upscope $end
$enddefinitions $end
#0
$dumpvars
b11110000111100001111000011110000111100001111000011110000111100001111000011110000111100001111 9
bx 8
07
16
b101111101110110110101101101111101110110110101101101111101110110110101101101111101110110110101101 5
b0 4
b0 3
b110010101011111110101101110010101011111110101101110010101011111110101101110010101011111110101101 2
01
00
b1011 /
b1010 .
b1100 -
0,
1+
b101111101110110110101101101111101110110110101101101111101110110110101101101111101110110110101101 *
b0 )
b110010101011111110101101110010101011111110101101110010101011111110101101110010101011111110101101 (
0'
0&
b1011 %
b1010 $
b1100 #
b11110000111100001111000011110000111100001111000011110000111100001111000011110000111100001111 "
x!
$end
#5
b101000001011000011000000101000001011000011000000101000001011000011000000101000001011000011000000 9
b101000001011000011000000101000001011000011000000101000001011000011000000101000001011000011000000 "
0!
b0 8
1'
11
#10
0'
01
#15
1'
11
#20
0'
01
#25
1'
11
#30
1!
0'
01
1,
17
0+
06
#35
1'
11
#40
0'
01
#45
1'
11
#50
0'
01
#55
1'
11
#60
0!
0'
01
0,
07
b1 )
b1 4
b1 3
#65
1'
11
#70
0'
01
#75
1'
11
#80
0'
01
#85
1'
11
#90
0'
01
1&
10
#95
b101111101110110110101101101111101110110110101101101111101110110110101101101111101110110110101101 9
b101111101110110110101101101111101110110110101101101111101110110110101101101111101110110110101101 "
1!
b1 8
1'
11
#100
0'
01
#105
1'
11
#110
0'
01
#115
1'
11
#120
0'
01
0&
00
#125
1'
11
#130
0'
01
#135
1'
11
#140
0'
01
#145
1'
11
#150
0'
01
1&
10
b10 )
b10 4
b10 3
#155
b110010101011111110101101110010101011111110101101110010101011111110101101110010101011111110101101 9
b110010101011111110101101110010101011111110101101110010101011111110101101110010101011111110101101 "
b10 8
1'
11
