ledControl.v
/*
Authored by Elijah Theander
November 08, 2016
ledControl.v
System Control module for driving many of the modules
needed for operation.
*/

module ledControl(doGen,doRet,loadRegister,genMode,go,retDone,sendDone,registerBit,clk,reset);
	output doGen;          //Control line saying start sending
	output doRet;          //Control line telling retCounter to count
	output loadRegister;   //Tells shiftRegister to grab a new value
	output [1:0] genMode;  //Tells bitGenerator what it's creating
	
	input go;              //Input from modeMachine
	input retDone;         //Input saying RET timing has been reached
	input sendDone;        //Input saying full 96 bits have been sent
	input registerBit;     //Bit to be sent.
	input clk,reset;       //Synchronous clock and reset
	
	//State parameters and variables
	parameter sendRet = 1'b0, sendBit = 1'b1;
	reg       S,nS;
	
	//State Memory
	always @(posedge clk)begin
		if(reset)begin
			S <= sendRet;
		end
		else begin
			S <= nS;
		end
	end
	
	//Next State
	always @(S,go,retDone,sendDone)begin
		case(S)
			sendRet:    nS = ((!retDone) ? sendRet : (go ? sendBit : sendRet);
			sendBit:    nS = sendDone ? sendRet : sendBit;
			default:    nS = sendRet;
		endcase
	end
	
	//Output assignments
	assign doGen = (S == sendBit);
	assign doRet = (S == sendRet);
	assign loadRegister = (S == sendRet);
	assign genMode = (S == sendRet) ? 2'b00 : {1'b1,registerBit};
	
endmodule

Test Benches/tb_ledControl.v
/*
Authored by Elijah Theander
November 10, 2016
tb_ledControl.v
Test bench for verifying control module.
*/

`timescale 1ns/1ns

module tb_ledControl;
	wire doGen;
	wire doRet;
	wire loadRegister;
	wire [1:0] genMode;
	
	reg go;
	reg retDone;
	reg sendDone;
	reg registerBit;
	reg clk,reset;
	
	//Module under test
	ledControl mut(doGen,doRet,loadRegister,genMode,go,retDone,sendDone,registerBit,clk,reset);
	
	//Set up 100 MHz clk
	always begin
		#5 clk = !clk;
	end
	
	//Begin testing stimulus
	initial begin
		$dumpfile("ledControl.vcd");
		$dumpvars(0,tb_ledControl);
			{go,retDone,sendDone,registerBit,clk,reset} = 6'b000001; #10 //initialize
			retDone = 1; reset  = 0;                                 #20 //state should stay at sendRet,doRet=1,loadRegister=1,genMode=00;
			go = 1;                                                  #20 //doGen=1,genMode=10
			registerBit=1;                                           #20 //genMode=11;
			sendDone=1;                                              #20 //state goes to sendRet.
			//doRet is high, loadregister is high, genMode is 00;
		$finish;
	end
	
endmodule

Test bench results/ledControl/ledControl.vcd
$date
	Thu Nov 10 16:22:12 2016
$end
$version
	Icarus Verilog
$end
$timescale
	1ns
$end
$scope module tb_ledControl $end
$var wire 1 ! doGen $end
$var wire 1 " doRet $end
$var wire 2 # genMode [1:0] $end
$var wire 1 $ loadRegister $end
$var reg 1 % clk $end
$var reg 1 & go $end
$var reg 1 ' registerBit $end
$var reg 1 ( reset $end
$var reg 1 ) retDone $end
$var reg 1 * sendDone $end
$scope module mut $end
$var wire 1 + clk $end
$var wire 1 ! doGen $end
$var wire 1 " doRet $end
$var wire 2 , genMode [1:0] $end
$var wire 1 - go $end
$var wire 1 $ loadRegister $end
$var wire 1 . registerBit $end
$var wire 1 / reset $end
$var wire 1 0 retDone $end
$var wire 1 1 sendDone $end
$var reg 1 2 S $end
$var reg 1 3 nS $end
$upscope $end
$upscope $end
$enddefinitions $end
#0
$dumpvars
03
x2
01
00
1/
0.
0-
bx0 ,
0+
0*
0)
1(
0'
0&
0%
x$
bx0 #
x"
x!
$end
#5
b0 #
b0 ,
02
0!
1"
1$
1%
1+
#10
0%
0+
0(
0/
1)
10
#15
1%
1+
#20
0%
0+
#25
1%
1+
#30
13
0%
0+
1&
1-
#35
b10 #
b10 ,
12
1!
0"
0$
1%
1+
#40
0%
0+
#45
1%
1+
#50
b11 #
b11 ,
0%
0+
1'
1.
#55
1%
1+
#60
0%
0+
#65
1%
1+
#70
03
0%
0+
1*
11
#75
13
b0 #
b0 ,
02
0!
1"
1$
1%
1+
#80
0%
0+
#85
03
b11 #
b11 ,
12
1!
0"
0$
1%
1+
